MANIFEST.in
README.rst
setup.py
examples/demo.py
examples/demo_net3.py
examples/demo_net4.py
examples/performance_net3.py
examples/performance_net4.py
examples/net3_ssa_10/log.txt
examples/net3_ssa_10/mean.tsd
examples/net3_ssa_10/percent-term-time.tsd
examples/net3_ssa_10/run-1.tsd
examples/net3_ssa_10/run-10.tsd
examples/net3_ssa_10/run-11.tsd
examples/net3_ssa_10/run-12.tsd
examples/net3_ssa_10/run-13.tsd
examples/net3_ssa_10/run-14.tsd
examples/net3_ssa_10/run-15.tsd
examples/net3_ssa_10/run-16.tsd
examples/net3_ssa_10/run-17.tsd
examples/net3_ssa_10/run-18.tsd
examples/net3_ssa_10/run-19.tsd
examples/net3_ssa_10/run-2.tsd
examples/net3_ssa_10/run-20.tsd
examples/net3_ssa_10/run-3.tsd
examples/net3_ssa_10/run-4.tsd
examples/net3_ssa_10/run-5.tsd
examples/net3_ssa_10/run-6.tsd
examples/net3_ssa_10/run-7.tsd
examples/net3_ssa_10/run-8.tsd
examples/net3_ssa_10/run-9.tsd
examples/net3_ssa_10/schematic_preferences.json
examples/net3_ssa_10/sim-rep.txt
examples/net3_ssa_10/standard_deviation.tsd
examples/net3_ssa_10/statistics.txt
examples/net3_ssa_10/term-time.tsd
examples/net3_ssa_10/term-time.txt
examples/net3_ssa_10/three.properties
examples/net3_ssa_10/three.xml
examples/net3_ssa_10/variance.tsd
examples/net3_ssa_100/log.txt
examples/net3_ssa_100/percent-term-time.tsd
examples/net3_ssa_100/run-1.tsd
examples/net3_ssa_100/run-10.tsd
examples/net3_ssa_100/run-11.tsd
examples/net3_ssa_100/run-12.tsd
examples/net3_ssa_100/run-13.tsd
examples/net3_ssa_100/run-14.tsd
examples/net3_ssa_100/run-15.tsd
examples/net3_ssa_100/run-16.tsd
examples/net3_ssa_100/run-17.tsd
examples/net3_ssa_100/run-18.tsd
examples/net3_ssa_100/run-19.tsd
examples/net3_ssa_100/run-2.tsd
examples/net3_ssa_100/run-20.tsd
examples/net3_ssa_100/run-3.tsd
examples/net3_ssa_100/run-4.tsd
examples/net3_ssa_100/run-5.tsd
examples/net3_ssa_100/run-6.tsd
examples/net3_ssa_100/run-7.tsd
examples/net3_ssa_100/run-8.tsd
examples/net3_ssa_100/run-9.tsd
examples/net3_ssa_100/schematic_preferences.json
pygenenet.egg-info/PKG-INFO
pygenenet.egg-info/SOURCES.txt
pygenenet.egg-info/dependency_links.txt
pygenenet.egg-info/not-zip-safe
pygenenet.egg-info/requires.txt
pygenenet.egg-info/top_level.txt