Metadata-Version: 1.0
Name: pygenenet
Version: 0.1.1
Summary: Python implementation of GeneNet algorithm (Barker et al. 2011)
Home-page: UNKNOWN
Author: Trang Tran
Author-email: ttdtrang@gmail.com
License: MIT
Platform: UNKNOWN
